spirvsmith_server_client/__init__.py
spirvsmith_server_client/api/__init__.py
spirvsmith_server_client/api/buffers/__init__.py
spirvsmith_server_client/api/buffers/post_buffers.py
spirvsmith_server_client/api/queues/__init__.py
spirvsmith_server_client/api/queues/delete_queues.py
spirvsmith_server_client/api/queues/get_queue.py
spirvsmith_server_client/api/queues/get_queues.py
spirvsmith_server_client/api/queues/register_executor.py
spirvsmith_server_client/api/shaders/__init__.py
spirvsmith_server_client/api/shaders/get_mismatches.py
spirvsmith_server_client/api/shaders/get_next_mismatch.py
spirvsmith_server_client/api/shaders/get_next_shader.py
spirvsmith_server_client/api/shaders/get_shader.py
spirvsmith_server_client/api/shaders/submit_shader.py
spirvsmith_server_client/client.py
spirvsmith_server_client/models/__init__.py
spirvsmith_server_client/models/buffer_submission.py
spirvsmith_server_client/models/execution_platform.py
spirvsmith_server_client/models/execution_platform_available_hardware.py
spirvsmith_server_client/models/execution_queue.py
spirvsmith_server_client/models/execution_queues.py
spirvsmith_server_client/models/execution_queues_queues.py
spirvsmith_server_client/models/hardware_information.py
spirvsmith_server_client/models/hardware_type.py
spirvsmith_server_client/models/hardware_vendor.py
spirvsmith_server_client/models/http_validation_error.py
spirvsmith_server_client/models/operating_system.py
spirvsmith_server_client/models/shader_data.py
spirvsmith_server_client/models/shader_submission.py
spirvsmith_server_client/models/validation_error.py
spirvsmith_server_client/models/vulkan_backend.py
spirvsmith_server_client/py.typed
spirvsmith_server_client/types.py
spirvsmith_server_client-0.3.0.dist-info/WHEEL
spirvsmith_server_client-0.3.0.dist-info/METADATA
spirvsmith_server_client-0.3.0.dist-info/RECORD
